talks_reducer/__about__.py
talks_reducer/__init__.py
talks_reducer/__main__.py
talks_reducer/audio.py
talks_reducer/chunks.py
talks_reducer/cli.py
talks_reducer/discovery.py
talks_reducer/ffmpeg.py
talks_reducer/icons.py
talks_reducer/models.py
talks_reducer/pipeline.py
talks_reducer/progress.py
talks_reducer/server.py
talks_reducer/server_tray.py
talks_reducer/service_client.py
talks_reducer/version_utils.py
talks_reducer/gui/__init__.py
talks_reducer/gui/__main__.py
talks_reducer/gui/app.py
talks_reducer/gui/discovery.py
talks_reducer/gui/hi_dpi.py
talks_reducer/gui/layout.py
talks_reducer/gui/preferences.py
talks_reducer/gui/progress.py
talks_reducer/gui/remote.py
talks_reducer/gui/startup.py
talks_reducer/gui/theme.py
talks_reducer/pyinstaller_hooks/__init__.py
talks_reducer/pyinstaller_hooks/tkinter_env.py
talks_reducer/resources/__init__.py
talks_reducer/resources/icons/app-256.png
talks_reducer/resources/icons/app.icns
talks_reducer/resources/icons/app.ico
talks_reducer-0.9.5.dist-info/licenses/LICENSE
talks_reducer-0.9.5.dist-info/METADATA
talks_reducer-0.9.5.dist-info/WHEEL
talks_reducer-0.9.5.dist-info/entry_points.txt
talks_reducer-0.9.5.dist-info/top_level.txt
talks_reducer-0.9.5.dist-info/RECORD
