Metadata-Version: 2.4
Name: talks-reducer
Version: 0.9.5
Summary: CLI for speeding up long-form talks by removing silence
Author: Talks Reducer Maintainers
License-Expression: MIT
Requires-Python: >=3.9
License-File: LICENSE
Requires-Dist: audiotsm>=0.1.2
Requires-Dist: scipy>=1.10.0
Requires-Dist: numpy>=1.22.0
Requires-Dist: tqdm>=4.65.0
Requires-Dist: tkinterdnd2>=0.3.0
Requires-Dist: Pillow>=9.0.0
Requires-Dist: pystray>=0.19.5
Requires-Dist: static-ffmpeg>=2.13
Requires-Dist: gradio>=4.0.0
Provides-Extra: dev
Requires-Dist: build>=1.0.0; extra == "dev"
Requires-Dist: twine>=4.0.0; extra == "dev"
Requires-Dist: pytest>=7.0.0; extra == "dev"
Requires-Dist: black>=23.0.0; extra == "dev"
Requires-Dist: isort>=5.12.0; extra == "dev"
Requires-Dist: bump-my-version>=0.5.0; extra == "dev"
Requires-Dist: pyinstaller>=6.4.0; extra == "dev"
Dynamic: license-file
